txwebbackendbase/__init__.py
txwebbackendbase/logging.py
txwebbackendbase/requests.py
txwebbackendbase/singleton.py
txwebbackendbase/threading.py
txwebbackendbase/txutils.py
txwebbackendbase/utils.py
txwebbackendbase/tests/__init__.py
txwebbackendbase/tests/test_logging.py
txwebbackendbase/tests/test_txwebbackendbase.py
txwebbackendbase-0.2.1.dist-info/DESCRIPTION.rst
txwebbackendbase-0.2.1.dist-info/METADATA
txwebbackendbase-0.2.1.dist-info/RECORD
txwebbackendbase-0.2.1.dist-info/WHEEL
txwebbackendbase-0.2.1.dist-info/metadata.json
txwebbackendbase-0.2.1.dist-info/pbr.json
txwebbackendbase-0.2.1.dist-info/top_level.txt
