Metadata-Version: 2.0
Name: txwebbackendbase
Version: 0.2.1
Summary: Generic Base framework for Web App backend using Twisted
Home-page: https://github.com/Stibbons/txwebbackendbase
Author: Gaetan Semet
Author-email: gaetan@xeberon.net
License: UNKNOWN
Platform: UNKNOWN
Classifier: Intended Audience :: Information Technology
Classifier: Intended Audience :: System Administrators
Classifier: License :: OSI Approved :: MIT License
Classifier: Operating System :: POSIX :: Linux
Classifier: Programming Language :: Python
Classifier: Programming Language :: Python :: 3
Classifier: Programming Language :: Python :: 3.4
Classifier: Programming Language :: Python :: 3.5
Classifier: Programming Language :: Python :: 3.6
Requires-Dist: pbr (>=3.0)
Requires-Dist: twisted (>=17.1)
